kirkush/.ipynb_checkpoints/__init__-checkpoint.py
kirkush/.ipynb_checkpoints/utils-checkpoint.ipynb
kirkush/__init__.py
kirkush/images/editing-1141505_1280.jpg
kirkush/kirkush/__init__.py
kirkush/kirkush/utils.ipynb
kirkush/tests/.ipynb_checkpoints/test_utils-checkpoint.ipynb
kirkush/tests/.ipynb_checkpoints/utils-checkpoint.ipynb
kirkush/tests/__init__.py
kirkush/tests/test_utils.ipynb
kirkush/tests/utils.ipynb
kirkush/videos/Raindrops_Videvo.mp4
kirkush/videos/South American Plants - Royalty Free Stock Footage [INN5AEpoE8w].mp4
kirkush/videos/Swimming In Ocean - Royalty Free Stock Footage [KLcWXzzgx-U].mp4
kirkush-0.1.6.dist-info/METADATA
kirkush-0.1.6.dist-info/WHEEL
kirkush-0.1.6.dist-info/RECORD
